my_moodle/__init__.py
my_moodle/__main__.py
my_moodle/api.py
my_moodle/api_functions.py
my_moodle/config_utility.py
my_moodle/course_markdown_builder.py
my_moodle/course_status.py
my_moodle/csv_utility.py
my_moodle/data_utility.py
my_moodle/enrolled_users_fields.py
my_moodle/json_utility.py
my_moodle/markdown_document.py
my_moodle/markdown_methods.py
my_moodle/moodle_data_downloader.py
my_moodle/moodle_json_downloader.py
my_moodle/notebook_utility.py
my_moodle/program_markdown_builder.py
my_moodle/project_structure.py
my_moodle/resource.json
my_moodle/resource_utility.py
my_moodle/update_utility.py
my_moodle/version.py
my_moodle/wrapper.py
tests/__init__.py
tests/main_test.py
tests/notebook_test.py
tests/version_test.py
my_moodle-0.4.6.dist-info/METADATA
my_moodle-0.4.6.dist-info/WHEEL
my_moodle-0.4.6.dist-info/license
my_moodle-0.4.6.dist-info/top_level.txt
my_moodle-0.4.6.dist-info/RECORD
