Metadata-Version: 2.1
Name: my-moodle
Version: 0.4.6
Summary: Download Moodle Course content.
Home-page: https://github.com/marcocrowe/my-moodle-py-pi/
Author: Mark Crowe
Author-email: 66536097+marcocrowe@users.noreply.github.com
Project-URL: Bug Tracker, https://github.com/marcocrowe/my-moodle-py-pi/issues
Classifier: Programming Language :: Python :: 3
Classifier: Operating System :: OS Independent
Requires-Python: >=3.9
License-File: license
Requires-Dist: requests ==2.32.2
